PuQTSqlite/__init__.py
PuQTSqlite/req/database.py
PuQTSqlite/req/main.py
PuQTSqlite/req/material_calc.py
PuQTSqlite/req/partners.db
PuQTSqlite/req/requirements.txt
PuQTSqlite/req/Мастер пол.png
PuQTSqlite-0.1.1.dist-info/LICENSE
PuQTSqlite-0.1.1.dist-info/METADATA
PuQTSqlite-0.1.1.dist-info/WHEEL
PuQTSqlite-0.1.1.dist-info/top_level.txt
PuQTSqlite-0.1.1.dist-info/RECORD
