Metadata-Version: 2.1
Name: PuQTSqlite
Version: 0.1.1
Summary: A package to distribute your PyQt SQLite program files
Home-page: https://github.com/yourusername/PuQTSqlite
Author: Your Name
Author-email: your.email@example.com
Classifier: Programming Language :: Python :: 3
Classifier: License :: OSI Approved :: MIT License
Classifier: Operating System :: OS Independent
Requires-Python: >=3.6
License-File: LICENSE
